unboil_sqlalchemy_types/__init__.py
unboil_sqlalchemy_types-0.1.7.dist-info/METADATA
unboil_sqlalchemy_types-0.1.7.dist-info/WHEEL
unboil_sqlalchemy_types-0.1.7.dist-info/licenses/LICENSE
unboil_sqlalchemy_types-0.1.7.dist-info/RECORD
