Metadata-Version: 2.4
Name: unboil-sqlalchemy-types
Version: 0.1.7
Summary: A library to expand SQLAlchemy types.
Project-URL: homepage, https://github.com/eyueldk/unboil-sqlalchemy-types
Project-URL: repository, https://github.com/eyueldk/unboil-sqlalchemy-types
Author: eyueldk
License: MIT
License-File: LICENSE
Keywords: pydantic,sqlalchemy,types,unboil
Classifier: Intended Audience :: Developers
Classifier: License :: OSI Approved :: MIT License
Classifier: Operating System :: OS Independent
Classifier: Programming Language :: Python :: 3
Classifier: Topic :: Software Development :: Libraries :: Python Modules
Requires-Python: >=3.9
Requires-Dist: sqlalchemy>=2.0.0
Provides-Extra: pydantic
Requires-Dist: pydantic>=2.0.0; extra == 'pydantic'
